{
  "batch": 21,
  "description": "Asian Schools Batch 21 - Middle East universities",
  "schools": [
    {
      "id": 10464,
      "name": "Technion - Israel Institute of Technology",
      "name_cn": "以色列理工学院",
      "region": "Asia",
      "country": "Israel",
      "city": "Haifa",
      "level": "university",
      "website": "https://www.technion.ac.il",
      "founded": 1912
    },
    {
      "id": 10465,
      "name": "Hebrew University of Jerusalem",
      "name_cn": "希伯来大学",
      "region": "Asia",
      "country": "Israel",
      "city": "Jerusalem",
      "level": "university",
      "website": "https://new.huji.ac.il",
      "founded": 1918
    },
    {
      "id": 10466,
      "name": "Tel Aviv University",
      "name_cn": "特拉维夫大学",
      "region": "Asia",
      "country": "Israel",
      "city": "Tel Aviv",
      "level": "university",
      "website": "https://www.tau.ac.il",
      "founded": 1956
    },
    {
      "id": 10467,
      "name": "Bar-Ilan University",
      "name_cn": "巴伊兰大学",
      "region": "Asia",
      "country": "Israel",
      "city": "Ramat Gan",
      "level": "university",
      "website": "https://www.biu.ac.il",
      "founded": 1955
    },
    {
      "id": 10468,
      "name": "Ben-Gurion University of the Negev",
      "name_cn": "本古里安大学",
      "region": "Asia",
      "country": "Israel",
      "city": "Beersheba",
      "level": "university",
      "website": "https://www.bgu.ac.il",
      "founded": 1969
    },
    {
      "id": 10469,
      "name": "American University of Beirut",
      "name_cn": "贝鲁特美国大学",
      "region": "Asia",
      "country": "Lebanon",
      "city": "Beirut",
      "level": "university",
      "website": "https://www.aub.edu.lb",
      "founded": 1866
    },
    {
      "id": 10470,
      "name": "Lebanese American University",
      "name_cn": "黎巴嫩美国大学",
      "region": "Asia",
      "country": "Lebanon",
      "city": "Byblos",
      "level": "university",
      "website": "https://www.lau.edu.lb",
      "founded": 1924
    },
    {
      "id": 10471,
      "name": "University of Jordan",
      "name_cn": "约旦大学",
      "region": "Asia",
      "country": "Jordan",
      "city": "Amman",
      "level": "university",
      "website": "https://www.ju.edu.jo",
      "founded": 1962
    },
    {
      "id": 10472,
      "name": "Jordan University of Science and Technology",
      "name_cn": "约旦科技大学",
      "region": "Asia",
      "country": "Jordan",
      "city": "Irbid",
      "level": "university",
      "website": "https://www.just.edu.jo",
      "founded": 1986
    },
    {
      "id": 10473,
      "name": "Hashemite University",
      "name_cn": "哈希姆大学",
      "region": "Asia",
      "country": "Jordan",
      "city": "Zarqa",
      "level": "university",
      "website": "https://www.hu.edu.jo",
      "founded": 1999
    },
    {
      "id": 10474,
      "name": "Cairo University",
      "name_cn": "开罗大学",
      "region": "Asia",
      "country": "Egypt",
      "city": "Cairo",
      "level": "university",
      "website": "https://www.cu.edu.eg",
      "founded": 1908
    },
    {
      "id": 10475,
      "name": "American University in Cairo",
      "name_cn": "开罗美国大学",
      "region": "Asia",
      "country": "Egypt",
      "city": "Cairo",
      "level": "university",
      "website": "https://www.aucegypt.edu",
      "founded": 1919
    },
    {
      "id": 10476,
      "name": "University of Tehran",
      "name_cn": "德黑兰大学",
      "region": "Asia",
      "country": "Iran",
      "city": "Tehran",
      "level": "university",
      "website": "https://ut.ac.ir",
      "founded": 1934
    },
    {
      "id": 10477,
      "name": "Sharif University of Technology",
      "name_cn": "谢里夫理工大学",
      "region": "Asia",
      "country": "Iran",
      "city": "Tehran",
      "level": "university",
      "website": "https://www.sharif.edu",
      "founded": 1966
    },
    {
      "id": 10478,
      "name": "Amirkabir University of Technology",
      "name_cn": "阿米尔卡比尔理工大学",
      "region": "Asia",
      "country": "Iran",
      "city": "Tehran",
      "level": "university",
      "website": "https://www.aut.ac.ir",
      "founded": 1958
    },
    {
      "id": 10479,
      "name": "Tehran University of Medical Sciences",
      "name_cn": "德黑兰医科大学",
      "region": "Asia",
      "country": "Iran",
      "city": "Tehran",
      "level": "university",
      "website": "https://tums.ac.ir",
      "founded": 1934
    },
    {
      "id": 10480,
      "name": "Isfahan University of Technology",
      "name_cn": "伊斯法罕理工大学",
      "region": "Asia",
      "country": "Iran",
      "city": "Isfahan",
      "level": "university",
      "website": "https://www.iut.ac.ir",
      "founded": 1974
    },
    {
      "id": 10481,
      "name": "University of Baghdad",
      "name_cn": "巴格达大学",
      "region": "Asia",
      "country": "Iraq",
      "city": "Baghdad",
      "level": "university",
      "website": "https://www.uobaghdad.edu.iq",
      "founded": 1957
    },
    {
      "id": 10482,
      "name": "American University of Iraq Sulaimani",
      "name_cn": "苏莱曼尼亚美国大学",
      "region": "Asia",
      "country": "Iraq",
      "city": "Sulaimani",
      "level": "university",
      "website": "https://www.auis.edu.krd",
      "founded": 1968
    },
    {
      "id": 10483,
      "name": "Kuwait University",
      "name_cn": "科威特大学",
      "region": "Asia",
      "country": "Kuwait",
      "city": "Kuwait City",
      "level": "university",
      "website": "https://www.ku.edu.kw",
      "founded": 1966
    },
    {
      "id": 10484,
      "name": "Qatar University",
      "name_cn": "卡塔尔大学",
      "region": "Asia",
      "country": "Qatar",
      "city": "Doha",
      "level": "university",
      "website": "https://www.qu.edu.qa",
      "founded": 1973
    }
  ]
}
