{
  "batch": 135,
  "description": "Asian Schools Batch 135 - Specialized & Regional Institutions",
  "date_added": "2026-02-20",
  "schools_added": 21,
  "total_asian_schools_in_db_before": 7166,
  "schools": [
    {
      "id": 20406,
      "name": "National University of Sciences and Technology Pakistan",
      "name_cn": "巴基斯坦国立科技大学",
      "region": "Asia",
      "country": "Pakistan",
      "city": "Islamabad",
      "level": "university",
      "website": "https://www.nust.edu.pk",
      "founded": 1991,
      "notes": "Added to batch 135"
    },
    {
      "id": 20407,
      "name": "Pakistan Institute of Engineering and Applied Sciences",
      "name_cn": "巴基斯坦工程与应用科学研究所",
      "region": "Asia",
      "country": "Pakistan",
      "city": "Islamabad",
      "level": "university",
      "website": "https://www.pieas.edu.pk",
      "founded": 1967,
      "notes": "Added to batch 135"
    },
    {
      "id": 20408,
      "name": "University of Karachi",
      "name_cn": "卡拉奇大学",
      "region": "Asia",
      "country": "Pakistan",
      "city": "Karachi",
      "level": "university",
      "website": "https://www.uok.edu.pk",
      "founded": 1951,
      "notes": "Added to batch 135"
    },
    {
      "id": 20409,
      "name": "Dhaka University",
      "name_cn": "达卡大学",
      "region": "Asia",
      "country": "Bangladesh",
      "city": "Dhaka",
      "level": "university",
      "website": "https://www.du.ac.bd",
      "founded": 1921,
      "notes": "Added to batch 135"
    },
    {
      "id": 20410,
      "name": "Bangladesh University of Engineering and Technology",
      "name_cn": "孟加拉工程技术大学",
      "region": "Asia",
      "country": "Bangladesh",
      "city": "Dhaka",
      "level": "university",
      "website": "https://www.buet.ac.bd",
      "founded": 1962,
      "notes": "Added to batch 135"
    },
    {
      "id": 20411,
      "name": "Royal University of Bhutan",
      "name_cn": "不丹皇家大学",
      "region": "Asia",
      "country": "Bhutan",
      "city": "Thimphu",
      "level": "university",
      "website": "https://www.rub.edu.bt",
      "founded": 2003,
      "notes": "Added to batch 135"
    },
    {
      "id": 20412,
      "name": "Jigme Dorji Wangchuck College of Science and Technology",
      "name_cn": "吉格梅多吉旺秋科学技术学院",
      "region": "Asia",
      "country": "Bhutan",
      "city": "Thimphu",
      "level": "university",
      "website": "https://www.jdwct.edu.bt",
      "founded": 2009,
      "notes": "Added to batch 135"
    },
    {
      "id": 20413,
      "name": "Royal University of Cambodia",
      "name_cn": "柬埔寨皇家大学",
      "region": "Asia",
      "country": "Cambodia",
      "city": "Phnom Penh",
      "level": "university",
      "website": "https://www.rup.edu.kh",
      "founded": 1980,
      "notes": "Added to batch 135"
    },
    {
      "id": 20414,
      "name": "National University of Management",
      "name_cn": "柬埔寨国家管理大学",
      "region": "Asia",
      "country": "Cambodia",
      "city": "Phnom Penh",
      "level": "university",
      "website": "https://www.num.edu.kh",
      "founded": 1989,
      "notes": "Added to batch 135"
    },
    {
      "id": 20415,
      "name": "Royal University of Law and Economics",
      "name_cn": "柬埔寨皇家法律经济大学",
      "region": "Asia",
      "country": "Cambodia",
      "city": "Phnom Penh",
      "level": "university",
      "website": "https://www.rule.edu.kh",
      "founded": 1949,
      "notes": "Added to batch 135"
    },
    {
      "id": 20416,
      "name": "National University of Laos",
      "name_cn": "老挝国立大学",
      "region": "Asia",
      "country": "Laos",
      "city": "Vientiane",
      "level": "university",
      "website": "https://www.nuol.edu.la",
      "founded": 1996,
      "notes": "Added to batch 135"
    },
    {
      "id": 20417,
      "name": "Savannakhet University",
      "name_cn": "沙湾拿吉大学",
      "region": "Asia",
      "country": "Laos",
      "city": "Savannakhet",
      "level": "university",
      "website": "https://www.sku.ac.la",
      "founded": 2009,
      "notes": "Added to batch 135"
    },
    {
      "id": 20418,
      "name": "Suranaree University of Technology",
      "name_cn": "素拉那立皇家大学",
      "region": "Asia",
      "country": "Thailand",
      "city": "Nakhon Ratchasima",
      "level": "university",
      "website": "https://www.sut.ac.th",
      "founded": 1990,
      "notes": "Added to batch 135"
    },
    {
      "id": 20419,
      "name": "Bangkok University",
      "name_cn": "曼谷大学",
      "region": "Asia",
      "country": "Thailand",
      "city": "Bangkok",
      "level": "university",
      "website": "https://www.bu.ac.th",
      "founded": 1962,
      "notes": "Added to batch 135"
    },
    {
      "id": 20420,
      "name": "Sri Lanka Institute of Information Technology",
      "name_cn": "斯里兰卡信息技术学院",
      "region": "Asia",
      "country": "Sri Lanka",
      "city": "Malabe",
      "level": "university",
      "website": "https://www.sliit.lk",
      "founded": 1999,
      "notes": "Added to batch 135"
    },
    {
      "id": 20421,
      "name": "University of Moratuwa",
      "name_cn": "莫拉图瓦大学",
      "region": "Asia",
      "country": "Sri Lanka",
      "city": "Moratuwa",
      "level": "university",
      "website": "https://www.uom.lk",
      "founded": 1942,
      "notes": "Added to batch 135"
    },
    {
      "id": 20422,
      "name": "Tashkent State University of Uzbek",
      "name_cn": "塔什干国立乌兹别克大学",
      "region": "Asia",
      "country": "Uzbekistan",
      "city": "Tashkent",
      "level": "university",
      "website": "https://tsuu.uz",
      "founded": 1918,
      "notes": "Added to batch 135"
    },
    {
      "id": 20423,
      "name": "Westminster International University in Tashkent",
      "name_cn": "塔什干西敏国际大学",
      "region": "Asia",
      "country": "Uzbekistan",
      "city": "Tashkent",
      "level": "university",
      "website": "https://wiuu.uz",
      "founded": 2002,
      "notes": "Added to batch 135"
    },
    {
      "id": 20424,
      "name": "Tajik National University",
      "name_cn": "塔吉克国立大学",
      "region": "Asia",
      "country": "Tajikistan",
      "city": "Dushanbe",
      "level": "university",
      "website": "https://www.tnu.tj",
      "founded": 1947,
      "notes": "Added to batch 135"
    },
    {
      "id": 20425,
      "name": "Kyrgyz National University",
      "name_cn": "吉尔吉斯国立大学",
      "region": "Asia",
      "country": "Kyrgyzstan",
      "city": "Bishkek",
      "level": "university",
      "website": "https://www.knu.kg",
      "founded": 1951,
      "notes": "Added to batch 135"
    },
    {
      "id": 20426,
      "name": "American University of Central Asia",
      "name_cn": "中亚美国大学",
      "region": "Asia",
      "country": "Kyrgyzstan",
      "city": "Bishkek",
      "level": "university",
      "website": "https://www.auca.kg",
      "founded": 1997,
      "notes": "Added to batch 135"
    }
  ],
  "notes": "Batch 135 adds specialized universities from Pakistan (3), Bangladesh (2), Bhutan (2), Cambodia (3), Laos (2), Thailand (2), Sri Lanka (2), Uzbekistan (2), Tajikistan (1), Kyrgyzstan (2)"
}
